yam_sort/__init__.py
yam_sort/differ.py
yam_sort/main.py
yam_sort/yams.py
yam_sort-1.0.dist-info/LICENSE
yam_sort-1.0.dist-info/METADATA
yam_sort-1.0.dist-info/WHEEL
yam_sort-1.0.dist-info/entry_points.txt
yam_sort-1.0.dist-info/top_level.txt
yam_sort-1.0.dist-info/RECORD
