Metadata-Version: 2.1
Name: yam-sort
Version: 1.0
Summary: does basic diff-ing of YAML files while ignoring key-order
Home-page: https://github.com/Crawfishpress/yam_sort
Author: John Crawford
Author-email: psp_dev@crawfishpress.com
License: MIT License
Keywords: yaml diff sort
Platform: UNKNOWN
Classifier: Development Status :: 3 - Alpha
Classifier: Environment :: Console
Classifier: Intended Audience :: Developers
Classifier: Intended Audience :: End Users/Desktop
Classifier: License :: OSI Approved :: MIT License
Classifier: Operating System :: Microsoft
Classifier: Operating System :: Microsoft :: Windows
Classifier: Operating System :: POSIX :: Linux
Classifier: Programming Language :: Python
Classifier: Programming Language :: Python :: 3 :: Only
Classifier: Programming Language :: Python :: 3.6
Classifier: Topic :: Software Development :: Libraries :: Python Modules
Requires-Python: >=3.6
Requires-Dist: PyYAML (==5.1.2)
